{
    "entries": [
        {
            "username": "bobo",
            "createdAtIso": "2025-08-14T19:32:44.9244860Z",
            "updatedAtIso": "2025-08-14T19:36:41.1046160Z",
            "version": 1
        },
        {
            "username": "kiki",
            "createdAtIso": "2025-08-14T19:37:14.8229980Z",
            "updatedAtIso": "2025-08-14T19:44:25.5188110Z",
            "version": 1
        }
    ],
    "sessions": [
        {
            "username": "bobo",
            "scene": "Tutorial 2",
            "sessionId": "aa6edcd5bce34f7d901cccf8a9929c19",
            "startedAtIso": "2025-08-14T19:33:41.4366180Z",
            "samples": [
                {
                    "tIso": "2025-08-14T19:33:41.1452450Z",
                    "type": "concentration",
                    "score": 76,
                    "z": 0.940035129802802,
                    "raw": 0.29438329832618029,
                    "alpha": 0.08711434857551172,
                    "beta": 0.07751183059084328,
                    "theta": 0.1761880569321026,
                    "gamma": 0.01367213489317028,
                    "label": "Neutral",
                    "count": 0,
                    "target": 0,
                    "elapsed": 0.0,
                    "mu_raw": 0.0,
                    "sigma_raw": 0.0,
                    "mu_gamma": 0.0,
                    "sigma_gamma": 0.0,
                    "mu_total": 0.0,
                    "sigma_total": 0.0
                },
                {
                    "tIso": "2025-08-14T19:33:46.1512990Z",
                    "type": "concentration",
                    "score": 87,
                    "z": 1.6160440261920764,
                    "raw": 0.3824448750289434,
                    "alpha": 0.10347620512234385,
                    "beta": 0.12542790368509189,
                    "theta": 0.22448714822424513,
                    "gamma": 0.04379801824535622,
                    "label": "High focus",
                    "count": 0,
                    "target": 0,
                    "elapsed": 0.0,
                    "mu_raw": 0.0,
                    "sigma_raw": 0.0,
                    "mu_gamma": 0.0,
                    "sigma_gamma": 0.0,
                    "mu_total": 0.0,
                    "sigma_total": 0.0
                },
                {
                    "tIso": "2025-08-14T19:33:51.1606620Z",
                    "type": "concentration",
                    "score": 76,
                    "z": 0.9513179087241878,
                    "raw": 0.2958530708494605,
                    "alpha": 0.08258006814875996,
                    "beta": 0.08459903070924521,
                    "theta": 0.20336940827900394,
                    "gamma": 0.014653376490189972,
                    "label": "Neutral",
                    "count": 0,
                    "target": 0,
                    "elapsed": 0.0,
                    "mu_raw": 0.0,
                    "sigma_raw": 0.0,
                    "mu_gamma": 0.0,
                    "sigma_gamma": 0.0,
                    "mu_total": 0.0,
                    "sigma_total": 0.0
                },
                {
                    "tIso": "2025-08-14T19:33:56.1768720Z",
                    "type": "concentration",
                    "score": 86,
                    "z": 1.5034430420076346,
                    "raw": 0.36777669498201268,
                    "alpha": 0.08090806390162232,
                    "beta": 0.10127453040906914,
                    "theta": 0.1944615606300641,
                    "gamma": 0.014585009642326452,
                    "label": "High focus",
                    "count": 0,
                    "target": 0,
                    "elapsed": 0.0,
                    "mu_raw": 0.0,
                    "sigma_raw": 0.0,
                    "mu_gamma": 0.0,
                    "sigma_gamma": 0.0,
                    "mu_total": 0.0,
                    "sigma_total": 0.0
                }
            ]
        },
        {
            "username": "bobo",
            "scene": "Tutorial 2",
            "sessionId": "2f63fe11be214216aa678f7ca03e463d",
            "startedAtIso": "2025-08-14T19:35:21.8004970Z",
            "samples": [
                {
                    "tIso": "2025-08-14T19:35:21.5834290Z",
                    "type": "concentration",
                    "score": 30,
                    "z": -0.6937815805038162,
                    "raw": 0.12375881316788905,
                    "alpha": 0.15810271602828658,
                    "beta": 0.062302218898412618,
                    "theta": 0.3453137058290463,
                    "gamma": 0.011987344310500817,
                    "label": "Neutral",
                    "count": 0,
                    "target": 0,
                    "elapsed": 0.0,
                    "mu_raw": 0.0,
                    "sigma_raw": 0.0,
                    "mu_gamma": 0.0,
                    "sigma_gamma": 0.0,
                    "mu_total": 0.0,
                    "sigma_total": 0.0
                },
                {
                    "tIso": "2025-08-14T19:35:26.6126130Z",
                    "type": "concentration",
                    "score": 79,
                    "z": 1.129113450919748,
                    "raw": 0.688841048441451,
                    "alpha": 0.11609984669249828,
                    "beta": 0.23436250887773417,
                    "theta": 0.2241274225843635,
                    "gamma": 0.05201906682763624,
                    "label": "High focus",
                    "count": 0,
                    "target": 0,
                    "elapsed": 0.0,
                    "mu_raw": 0.0,
                    "sigma_raw": 0.0,
                    "mu_gamma": 0.0,
                    "sigma_gamma": 0.0,
                    "mu_total": 0.0,
                    "sigma_total": 0.0
                },
                {
                    "tIso": "2025-08-14T19:35:31.6405220Z",
                    "type": "concentration",
                    "score": 69,
                    "z": 0.6812676099079565,
                    "raw": 0.5500125780498892,
                    "alpha": 0.1507246052941813,
                    "beta": 0.2240051867798652,
                    "theta": 0.2565482384897597,
                    "gamma": 0.04794850092121688,
                    "label": "Neutral",
                    "count": 0,
                    "target": 0,
                    "elapsed": 0.0,
                    "mu_raw": 0.0,
                    "sigma_raw": 0.0,
                    "mu_gamma": 0.0,
                    "sigma_gamma": 0.0,
                    "mu_total": 0.0,
                    "sigma_total": 0.0
                }
            ]
        },
        {
            "username": "kiki",
            "scene": "Tutorial 2",
            "sessionId": "bb372efe77c4481fbe521a87be36d5d8",
            "startedAtIso": "2025-08-14T19:40:25.1077850Z",
            "samples": [
                {
                    "tIso": "2025-08-14T19:40:24.1413770Z",
                    "type": "veto",
                    "score": 0,
                    "z": 0.0,
                    "raw": 0.0,
                    "alpha": 0.0,
                    "beta": 0.0,
                    "theta": 0.0,
                    "gamma": 0.0,
                    "label": "",
                    "count": 0,
                    "target": 0,
                    "elapsed": 0.0,
                    "mu_raw": 0.0,
                    "sigma_raw": 0.0,
                    "mu_gamma": 0.0,
                    "sigma_gamma": 0.0,
                    "mu_total": 0.0,
                    "sigma_total": 0.0
                },
                {
                    "tIso": "2025-08-14T19:40:28.9339080Z",
                    "type": "concentration",
                    "score": 12,
                    "z": -1.663406270504234,
                    "raw": 0.06667869175335269,
                    "alpha": 0.04416255314506243,
                    "beta": 0.021026057051427378,
                    "theta": 0.2711714238492221,
                    "gamma": 0.004171374670647269,
                    "label": "Low focus",
                    "count": 0,
                    "target": 0,
                    "elapsed": 0.0,
                    "mu_raw": 0.0,
                    "sigma_raw": 0.0,
                    "mu_gamma": 0.0,
                    "sigma_gamma": 0.0,
                    "mu_total": 0.0,
                    "sigma_total": 0.0
                },
                {
                    "tIso": "2025-08-14T19:40:33.9502850Z",
                    "type": "concentration",
                    "score": 17,
                    "z": -1.3109731142606285,
                    "raw": 0.1185247471747196,
                    "alpha": 0.04731817489358452,
                    "beta": 0.036706193682823778,
                    "theta": 0.26237405864981169,
                    "gamma": 0.003828875937409073,
                    "label": "Low focus",
                    "count": 0,
                    "target": 0,
                    "elapsed": 0.0,
                    "mu_raw": 0.0,
                    "sigma_raw": 0.0,
                    "mu_gamma": 0.0,
                    "sigma_gamma": 0.0,
                    "mu_total": 0.0,
                    "sigma_total": 0.0
                },
                {
                    "tIso": "2025-08-14T19:40:38.9673290Z",
                    "type": "concentration",
                    "score": 59,
                    "z": 0.301743368072565,
                    "raw": 0.3557697016880358,
                    "alpha": 0.1280953005014768,
                    "beta": 0.14583708158634665,
                    "theta": 0.2818246024414422,
                    "gamma": 0.02792437932472037,
                    "label": "Neutral",
                    "count": 0,
                    "target": 0,
                    "elapsed": 0.0,
                    "mu_raw": 0.0,
                    "sigma_raw": 0.0,
                    "mu_gamma": 0.0,
                    "sigma_gamma": 0.0,
                    "mu_total": 0.0,
                    "sigma_total": 0.0
                },
                {
                    "tIso": "2025-08-14T19:40:43.9844640Z",
                    "type": "concentration",
                    "score": 13,
                    "z": -1.610317917553023,
                    "raw": 0.07448846118218329,
                    "alpha": 0.0685121995775669,
                    "beta": 0.024263411247363029,
                    "theta": 0.2572216236510441,
                    "gamma": 0.005355461035711929,
                    "label": "Low focus",
                    "count": 0,
                    "target": 0,
                    "elapsed": 0.0,
                    "mu_raw": 0.0,
                    "sigma_raw": 0.0,
                    "mu_gamma": 0.0,
                    "sigma_gamma": 0.0,
                    "mu_total": 0.0,
                    "sigma_total": 0.0
                },
                {
                    "tIso": "2025-08-14T19:40:49.0069220Z",
                    "type": "concentration",
                    "score": 23,
                    "z": -0.9999991905572508,
                    "raw": 0.1642717803278121,
                    "alpha": 0.06925229388897951,
                    "beta": 0.05718552295077788,
                    "theta": 0.2788630235227952,
                    "gamma": 0.01019927536203088,
                    "label": "Neutral",
                    "count": 0,
                    "target": 0,
                    "elapsed": 0.0,
                    "mu_raw": 0.0,
                    "sigma_raw": 0.0,
                    "mu_gamma": 0.0,
                    "sigma_gamma": 0.0,
                    "mu_total": 0.0,
                    "sigma_total": 0.0
                },
                {
                    "tIso": "2025-08-14T19:40:54.0287420Z",
                    "type": "concentration",
                    "score": 91,
                    "z": 1.9103451870735385,
                    "raw": 0.5924093525873666,
                    "alpha": 0.1948615083884621,
                    "beta": 0.20146792895226429,
                    "theta": 0.14522078111583817,
                    "gamma": 0.03546395328950185,
                    "label": "High focus",
                    "count": 0,
                    "target": 0,
                    "elapsed": 0.0,
                    "mu_raw": 0.0,
                    "sigma_raw": 0.0,
                    "mu_gamma": 0.0,
                    "sigma_gamma": 0.0,
                    "mu_total": 0.0,
                    "sigma_total": 0.0
                },
                {
                    "tIso": "2025-08-14T19:40:59.0546460Z",
                    "type": "concentration",
                    "score": 21,
                    "z": -1.1173152374444473,
                    "raw": 0.14701354522428773,
                    "alpha": 0.08676888704851636,
                    "beta": 0.06098510780051878,
                    "theta": 0.328057567937868,
                    "gamma": 0.010873156726229397,
                    "label": "Low focus",
                    "count": 0,
                    "target": 0,
                    "elapsed": 0.0,
                    "mu_raw": 0.0,
                    "sigma_raw": 0.0,
                    "mu_gamma": 0.0,
                    "sigma_gamma": 0.0,
                    "mu_total": 0.0,
                    "sigma_total": 0.0
                },
                {
                    "tIso": "2025-08-14T19:41:04.0734140Z",
                    "type": "concentration",
                    "score": 27,
                    "z": -0.8109337401267083,
                    "raw": 0.1920849915641356,
                    "alpha": 0.05133631000597772,
                    "beta": 0.06369182665789584,
                    "theta": 0.2802451745184787,
                    "gamma": 0.013222844001622865,
                    "label": "Neutral",
                    "count": 0,
                    "target": 0,
                    "elapsed": 0.0,
                    "mu_raw": 0.0,
                    "sigma_raw": 0.0,
                    "mu_gamma": 0.0,
                    "sigma_gamma": 0.0,
                    "mu_total": 0.0,
                    "sigma_total": 0.0
                },
                {
                    "tIso": "2025-08-14T19:41:09.1002140Z",
                    "type": "concentration",
                    "score": 77,
                    "z": 1.0032467579961094,
                    "raw": 0.45896709667749416,
                    "alpha": 0.10459216874708802,
                    "beta": 0.15322429505513089,
                    "theta": 0.22925375651395353,
                    "gamma": 0.02430469929669658,
                    "label": "High focus",
                    "count": 0,
                    "target": 0,
                    "elapsed": 0.0,
                    "mu_raw": 0.0,
                    "sigma_raw": 0.0,
                    "mu_gamma": 0.0,
                    "sigma_gamma": 0.0,
                    "mu_total": 0.0,
                    "sigma_total": 0.0
                },
                {
                    "tIso": "2025-08-14T19:41:14.1220910Z",
                    "type": "concentration",
                    "score": 36,
                    "z": -0.4653327873719414,
                    "raw": 0.2429259690169372,
                    "alpha": 0.09276389088411596,
                    "beta": 0.09290962253074588,
                    "theta": 0.28969675301692845,
                    "gamma": 0.01565171713728992,
                    "label": "Neutral",
                    "count": 0,
                    "target": 0,
                    "elapsed": 0.0,
                    "mu_raw": 0.0,
                    "sigma_raw": 0.0,
                    "mu_gamma": 0.0,
                    "sigma_gamma": 0.0,
                    "mu_total": 0.0,
                    "sigma_total": 0.0
                },
                {
                    "tIso": "2025-08-14T19:41:19.1425400Z",
                    "type": "concentration",
                    "score": 95,
                    "z": 2.4658886820204186,
                    "raw": 0.6741347473685746,
                    "alpha": 0.13623214403911944,
                    "beta": 0.23282711439745866,
                    "theta": 0.2091396311224556,
                    "gamma": 0.056124281277828657,
                    "label": "High focus",
                    "count": 0,
                    "target": 0,
                    "elapsed": 0.0,
                    "mu_raw": 0.0,
                    "sigma_raw": 0.0,
                    "mu_gamma": 0.0,
                    "sigma_gamma": 0.0,
                    "mu_total": 0.0,
                    "sigma_total": 0.0
                },
                {
                    "tIso": "2025-08-14T19:41:24.1514320Z",
                    "type": "concentration",
                    "score": 64,
                    "z": 0.4972932167712458,
                    "raw": 0.38453682564802979,
                    "alpha": 0.14969876676433853,
                    "beta": 0.1914781327017105,
                    "theta": 0.3482460851458598,
                    "gamma": 0.04935115756085907,
                    "label": "Neutral",
                    "count": 0,
                    "target": 0,
                    "elapsed": 0.0,
                    "mu_raw": 0.0,
                    "sigma_raw": 0.0,
                    "mu_gamma": 0.0,
                    "sigma_gamma": 0.0,
                    "mu_total": 0.0,
                    "sigma_total": 0.0
                },
                {
                    "tIso": "2025-08-14T19:41:29.1791260Z",
                    "type": "concentration",
                    "score": 97,
                    "z": 2.856096862455763,
                    "raw": 0.7315378452051978,
                    "alpha": 0.1484674268410886,
                    "beta": 0.267099974272071,
                    "theta": 0.2166537709506913,
                    "gamma": 0.06495880615270268,
                    "label": "High focus",
                    "count": 0,
                    "target": 0,
                    "elapsed": 0.0,
                    "mu_raw": 0.0,
                    "sigma_raw": 0.0,
                    "mu_gamma": 0.0,
                    "sigma_gamma": 0.0,
                    "mu_total": 0.0,
                    "sigma_total": 0.0
                },
                {
                    "tIso": "2025-08-14T19:41:34.2045160Z",
                    "type": "concentration",
                    "score": 99,
                    "z": 3.5931062249980876,
                    "raw": 0.8399584849194243,
                    "alpha": 0.13664247415544485,
                    "beta": 0.3056785679352163,
                    "theta": 0.22727856887527066,
                    "gamma": 0.06831627080180233,
                    "label": "High focus",
                    "count": 0,
                    "target": 0,
                    "elapsed": 0.0,
                    "mu_raw": 0.0,
                    "sigma_raw": 0.0,
                    "mu_gamma": 0.0,
                    "sigma_gamma": 0.0,
                    "mu_total": 0.0,
                    "sigma_total": 0.0
                },
                {
                    "tIso": "2025-08-14T19:41:39.2238520Z",
                    "type": "concentration",
                    "score": 27,
                    "z": -0.8150494760769068,
                    "raw": 0.1914795301584947,
                    "alpha": 0.09309020758372842,
                    "beta": 0.07111433424407347,
                    "theta": 0.2783037173178944,
                    "gamma": 0.013840095941090336,
                    "label": "Neutral",
                    "count": 0,
                    "target": 0,
                    "elapsed": 0.0,
                    "mu_raw": 0.0,
                    "sigma_raw": 0.0,
                    "mu_gamma": 0.0,
                    "sigma_gamma": 0.0,
                    "mu_total": 0.0,
                    "sigma_total": 0.0
                },
                {
                    "tIso": "2025-08-14T19:41:44.2420150Z",
                    "type": "concentration",
                    "score": 20,
                    "z": -1.1300983355022545,
                    "raw": 0.14513303767662745,
                    "alpha": 0.09223172111688284,
                    "beta": 0.05699843354220848,
                    "theta": 0.3005005916254592,
                    "gamma": 0.012847552851888033,
                    "label": "Low focus",
                    "count": 0,
                    "target": 0,
                    "elapsed": 0.0,
                    "mu_raw": 0.0,
                    "sigma_raw": 0.0,
                    "mu_gamma": 0.0,
                    "sigma_gamma": 0.0,
                    "mu_total": 0.0,
                    "sigma_total": 0.0
                },
                {
                    "tIso": "2025-08-14T19:41:49.2641740Z",
                    "type": "concentration",
                    "score": 87,
                    "z": 1.5790570107502456,
                    "raw": 0.5436739119915652,
                    "alpha": 0.1336609371417143,
                    "beta": 0.2533528715877572,
                    "theta": 0.33234058693204729,
                    "gamma": 0.03146031761485018,
                    "label": "High focus",
                    "count": 0,
                    "target": 0,
                    "elapsed": 0.0,
                    "mu_raw": 0.0,
                    "sigma_raw": 0.0,
                    "mu_gamma": 0.0,
                    "sigma_gamma": 0.0,
                    "mu_total": 0.0,
                    "sigma_total": 0.0
                },
                {
                    "tIso": "2025-08-14T19:41:54.2884690Z",
                    "type": "concentration",
                    "score": 25,
                    "z": -0.9362162227223064,
                    "raw": 0.17365482283310924,
                    "alpha": 0.056137608863059459,
                    "beta": 0.044540547257799458,
                    "theta": 0.20035136467055468,
                    "gamma": 0.010059532468024164,
                    "label": "Neutral",
                    "count": 0,
                    "target": 0,
                    "elapsed": 0.0,
                    "mu_raw": 0.0,
                    "sigma_raw": 0.0,
                    "mu_gamma": 0.0,
                    "sigma_gamma": 0.0,
                    "mu_total": 0.0,
                    "sigma_total": 0.0
                }
            ]
        },
        {
            "username": "kiki",
            "scene": "Sonification_J",
            "sessionId": "68e5e63da3d34700b244a318c7017dbd",
            "startedAtIso": "2025-08-14T19:44:20.4989640Z",
            "samples": [
                {
                    "tIso": "2025-08-14T19:44:20.0306510Z",
                    "type": "concentration",
                    "score": 39,
                    "z": -0.3765736329557241,
                    "raw": 0.2997554382089144,
                    "alpha": 0.217803762617466,
                    "beta": 0.14645709132894225,
                    "theta": 0.2707848421589695,
                    "gamma": 0.025979250901292,
                    "label": "Neutral",
                    "count": 0,
                    "target": 0,
                    "elapsed": 0.0,
                    "mu_raw": 0.0,
                    "sigma_raw": 0.0,
                    "mu_gamma": 0.0,
                    "sigma_gamma": 0.0,
                    "mu_total": 0.0,
                    "sigma_total": 0.0
                },
                {
                    "tIso": "2025-08-14T19:44:25.0526830Z",
                    "type": "concentration",
                    "score": 86,
                    "z": 1.4810115908542277,
                    "raw": 0.7153455873612904,
                    "alpha": 0.12286899342369824,
                    "beta": 0.236142258765141,
                    "theta": 0.2072403452464239,
                    "gamma": 0.07637665516486232,
                    "label": "High focus",
                    "count": 0,
                    "target": 0,
                    "elapsed": 0.0,
                    "mu_raw": 0.0,
                    "sigma_raw": 0.0,
                    "mu_gamma": 0.0,
                    "sigma_gamma": 0.0,
                    "mu_total": 0.0,
                    "sigma_total": 0.0
                }
            ]
        }
    ]
}